setup.py
Analyzer_zero.egg-info/PKG-INFO
Analyzer_zero.egg-info/SOURCES.txt
Analyzer_zero.egg-info/dependency_links.txt
Analyzer_zero.egg-info/not-zip-safe
Analyzer_zero.egg-info/requires.txt
Analyzer_zero.egg-info/top_level.txt
analyzerlibs/__init__.py
analyzerlibs/classify/__init__.py
analyzerlibs/classify/web.py
analyzerlibs/graphy/__init__.py
analyzerlibs/nerual/__init__.py
analyzerlibs/nerual/_nerual.py
analyzerlibs/wordslib/__init__.py
analyzerlibs/wordslib/stat.py