Metadata-Version: 1.0
Name: Analyzer-zero
Version: 0.3
Summary: a anayzer package
Home-page: https://github.com/Qingluan/.git
Author: Qing luan
Author-email: darkhackdevil@gmail.com
License: MIT
Platform: UNKNOWN
